ir_measures/__init__.py
ir_measures/__main__.py
ir_measures/lazylibs.py
ir_measures/py.typed
ir_measures/util.py
ir_measures/bin/__init__.py
ir_measures/bin/gdeval.pl
ir_measures/bin/msmarco_eval.py
ir_measures/measures/__init__.py
ir_measures/measures/accuracy.py
ir_measures/measures/ap.py
ir_measures/measures/base.py
ir_measures/measures/bpm.py
ir_measures/measures/bpref.py
ir_measures/measures/compat.py
ir_measures/measures/diversity.py
ir_measures/measures/err.py
ir_measures/measures/infap.py
ir_measures/measures/inst.py
ir_measures/measures/iprec.py
ir_measures/measures/judged.py
ir_measures/measures/ndcg.py
ir_measures/measures/nerr.py
ir_measures/measures/numq.py
ir_measures/measures/numrel.py
ir_measures/measures/numret.py
ir_measures/measures/p.py
ir_measures/measures/r.py
ir_measures/measures/rbp.py
ir_measures/measures/rprec.py
ir_measures/measures/rr.py
ir_measures/measures/sdcg.py
ir_measures/measures/set_measures.py
ir_measures/measures/success.py
ir_measures/providers/__init__.py
ir_measures/providers/accuracy_provider.py
ir_measures/providers/base.py
ir_measures/providers/compat_provider.py
ir_measures/providers/cwl_eval.py
ir_measures/providers/fallback_provider.py
ir_measures/providers/gdeval_provider.py
ir_measures/providers/judged_provider.py
ir_measures/providers/msmarco_provider.py
ir_measures/providers/pyndeval_provider.py
ir_measures/providers/pytrec_eval_provider.py
ir_measures/providers/ranx_provider.py
ir_measures/providers/runtime_provider.py
ir_measures/providers/trectools_provider.py
ir_measures-0.4.2.dist-info/licenses/LICENSE.txt
ir_measures-0.4.2.dist-info/METADATA
ir_measures-0.4.2.dist-info/WHEEL
ir_measures-0.4.2.dist-info/entry_points.txt
ir_measures-0.4.2.dist-info/top_level.txt
ir_measures-0.4.2.dist-info/RECORD
