Metadata-Version: 2.4
Name: ir_measures
Version: 0.4.2
Summary: Provides a common interface to many IR measure tools
Author-email: Sean MacAvaney <sean.macavaney@glasgow.ac.uk>
Maintainer-email: Sean MacAvaney <sean.macavaney@glasgow.ac.uk>
Project-URL: Repository, https://github.com/terrierteam/ir_measures
Project-URL: Bug Tracker, https://github.com/terrierteam/ir_measures/issues
Classifier: License :: OSI Approved :: Apache Software License
Classifier: Programming Language :: Python
Classifier: Topic :: Scientific/Engineering :: Information Analysis
Classifier: Operating System :: OS Independent
Requires-Python: >=3.9
License-File: LICENSE.txt
Requires-Dist: pytrec-eval-terrier>=0.5.5
Provides-Extra: cwl-eval
Requires-Dist: cwl-eval>=1.0.10; extra == "cwl-eval"
Provides-Extra: pyndeval
Requires-Dist: pyndeval>=0.0.6; extra == "pyndeval"
Provides-Extra: trectools
Requires-Dist: trectools>=0.0.44; extra == "trectools"
Provides-Extra: ranx
Requires-Dist: ranx>=0.1.11; extra == "ranx"
Dynamic: license-file
